gigaml/__init__.py
gigaml/utils.py
gigaml/wrapper.py
gigaml/core_client/__init__.py
gigaml/core_client/client.py
gigaml/core_client/environment.py
gigaml/core_client/core/__init__.py
gigaml/core_client/core/api_error.py
gigaml/core_client/core/client_wrapper.py
gigaml/core_client/core/datetime_utils.py
gigaml/core_client/core/jsonable_encoder.py
gigaml/core_client/core/remove_none_from_dict.py
gigaml/core_client/errors/__init__.py
gigaml/core_client/errors/bad_request_error.py
gigaml/core_client/types/__init__.py
gigaml/core_client/types/bad_request_error_body.py
gigaml/core_client/types/file.py
gigaml/core_client/types/file_status.py
gigaml/core_client/types/list_files_response.py
gigaml/core_client/types/log_response.py
gigaml-0.1.6.dist-info/METADATA
gigaml-0.1.6.dist-info/WHEEL
gigaml-0.1.6.dist-info/top_level.txt
gigaml-0.1.6.dist-info/RECORD
