Metadata-Version: 2.1
Name: gigaml
Version: 0.1.6
Summary: GigaML python sdk
Author: Esha Manideep Dinne
Author-email: founders@gigaml.com
